pyomt5/__init__.py
pyomt5/api/__init__.py
pyomt5/api/metatradercom.py
pyomt5/api/timeframe.py
pyomt5/stock/__init__.py
pyomt5/stock/history.py
pyOMT5-0.0.29.dist-info/LICENSE
pyOMT5-0.0.29.dist-info/METADATA
pyOMT5-0.0.29.dist-info/WHEEL
pyOMT5-0.0.29.dist-info/top_level.txt
pyOMT5-0.0.29.dist-info/RECORD
