Metadata-Version: 2.1
Name: pyOMT5
Version: 0.0.29
Summary: pyOMT5 - Python Open Metatrader 5 module
Home-page: https://github.com/paulorodriguesxv/pyomt5
Author: Paulo Rodrigues
Author-email: paulorodriguesxv@gmail.com
License: MIT
Keywords: stocks,market,finance,metatrader,quotes,shares
Platform: UNKNOWN
Classifier: Development Status :: 4 - Beta
Classifier: Intended Audience :: Developers
Classifier: Topic :: Office/Business :: Financial :: Investment
Classifier: License :: OSI Approved :: MIT License
Classifier: Programming Language :: Python :: 3.7
Requires-Dist: pyzmq
Requires-Dist: pandas
Provides-Extra: pandas
Requires-Dist: pandas ; extra == 'pandas'
